dagster_cube/__init__.py
dagster_cube/cube_resource.py
dagster_cube-0.1.0.dist-info/METADATA
dagster_cube-0.1.0.dist-info/WHEEL
dagster_cube-0.1.0.dist-info/RECORD
