Metadata-Version: 2.1
Name: dagster-cube
Version: 0.1.0
Summary: Dagster library to interact with Cube.js
Author: Olivier Dupuis
Author-email: odupuis@lantrns.co
Requires-Python: >=3.8
Classifier: Programming Language :: Python :: 3
Classifier: Programming Language :: Python :: 3.8
Classifier: Programming Language :: Python :: 3.9
Classifier: Programming Language :: Python :: 3.10
Classifier: Programming Language :: Python :: 3.11
Requires-Dist: dagster (>=1.2.0,<2.0.0)
